scst_proxy/__init__.py
scst_proxy/admin.py
scst_proxy/apps.py
scst_proxy/forms.py
scst_proxy/helpers.py
scst_proxy/hooks.py
scst_proxy/menu.py
scst_proxy/models.py
scst_proxy/signals.py
scst_proxy/tasks.py
scst_proxy/urls.py
scst_proxy/views.py
scst_proxy/migrations/0001_initial.py
scst_proxy/migrations/0002_alter_pluginsettings_options.py
scst_proxy/migrations/0003_alter_pluginsettings_options.py
scst_proxy/migrations/0004_pluginsettings_proxy_address.py
scst_proxy/migrations/0005_alter_pluginsettings_options.py
scst_proxy/migrations/__init__.py
scst_proxy/templates/scst_proxy/main.html
scst_proxy-0.6.9.dist-info/METADATA
scst_proxy-0.6.9.dist-info/WHEEL
scst_proxy-0.6.9.dist-info/top_level.txt
scst_proxy-0.6.9.dist-info/RECORD
