Metadata-Version: 2.1
Name: scst_proxy
Version: 0.6.9
Summary: Register user on SCST proxy server
Author: Aleksey Misyagin
Author-email: me@misyagin.ru
Requires-Dist: allianceauth>=2.11
Requires-Dist: requests
Requires-Dist: django-ipware
